agon/__init__.py
agon/agon_core.cpython-312-aarch64-linux-gnu.so
agon/core.py
agon/errors.py
agon/py.typed
agon_python-0.2.0.dist-info/METADATA
agon_python-0.2.0.dist-info/WHEEL
agon_python-0.2.0.dist-info/licenses/LICENSE
agon_python-0.2.0.dist-info/RECORD
