Metadata-Version: 2.4
Name: agon-python
Version: 0.2.0
Classifier: Development Status :: 4 - Beta
Classifier: Intended Audience :: Developers
Classifier: License :: OSI Approved :: MIT License
Classifier: Operating System :: OS Independent
Classifier: Programming Language :: Python
Classifier: Programming Language :: Python :: 3
Classifier: Programming Language :: Python :: 3.11
Classifier: Programming Language :: Python :: 3.12
Classifier: Programming Language :: Python :: 3.13
Classifier: Programming Language :: Rust
Classifier: Topic :: Scientific/Engineering :: Artificial Intelligence
Classifier: Topic :: Software Development :: Libraries :: Python Modules
Classifier: Typing :: Typed
Requires-Dist: orjson>=3.11.5
License-File: LICENSE
Summary: Adaptive Guarded Object Notation - A schema-driven, token-efficient data interchange format for LLMs
Keywords: llm,json,compression,tokens,schema,encoding,ai,machine-learning,data-interchange
Author-email: Harvey Tseng <harveytseng2@gmail.com>
License: MIT
Requires-Python: >=3.11, <4.0
Project-URL: Repository, https://github.com/Verdenroz/agon-python
Project-URL: Issues, https://github.com/Verdenroz/agon-python/issues
Project-URL: Documentation, https://github.com/Verdenroz/agon-python#readme
Project-URL: Changelog, https://github.com/Verdenroz/agon-python/releases
